firstgame2/FirstGame2.py
firstgame2/__init__.py
firstgame2-0.1.0.dist-info/WHEEL
firstgame2-0.1.0.dist-info/METADATA
firstgame2-0.1.0.dist-info/RECORD
